flika/__init__.py
flika/flika.py
flika/global_vars.py
flika/logger.py
flika/roi.py
flika/tracefig.py
flika/update_flika.py
flika/version.py
flika/window.py
flika/app/__init__.py
flika/app/application.py
flika/app/ipythonWidget.ui
flika/app/main.ui
flika/app/plugin_manager.py
flika/app/plugin_manager.ui
flika/app/plugin_utils.py
flika/app/script_editor.py
flika/app/script_namespace.py
flika/app/settings_editor.py
flika/app/syntax.py
flika/app/terminal.py
flika/docs/conf.py
flika/docs/sphinx_howto.txt
flika/docs/_static/img/favicon.ico
flika/docs/_static/img/flika_logo.png
flika/docs/api/app/__init__.py
flika/images/__init__.py
flika/images/check.png
flika/images/exclamation.png
flika/images/favicon.ico
flika/images/favicon.png
flika/images/freehand.png
flika/images/line.png
flika/images/mouse.png
flika/images/pencil.png
flika/images/point.png
flika/images/rect_line.png
flika/images/rectangle.png
flika/images/refresh.png
flika/images/search.png
flika/process/__init__.py
flika/process/binary.py
flika/process/color.py
flika/process/file_.py
flika/process/filters.py
flika/process/math_.py
flika/process/measure.py
flika/process/overlay.py
flika/process/progress_bar.py
flika/process/roi.py
flika/process/stacks.py
flika/tests/__init__.py
flika/tests/conftest.py
flika/tests/test_file.py
flika/tests/test_macros.py
flika/tests/test_misc.py
flika/tests/test_plugin_info.py
flika/tests/test_processes.py
flika/tests/test_settings.py
flika/tests/test_window.py
flika/tests/test_images/tubhiswt-2D/tubhiswt_C0.ome.tif
flika/tests/test_images/tubhiswt-2D/tubhiswt_C1.ome.tif
flika/tests/test_images/tubhiswt-3D/tubhiswt_C0.ome.tif
flika/tests/test_images/tubhiswt-3D/tubhiswt_C1.ome.tif
flika/utils/BaseProcess.py
flika/utils/__init__.py
flika/utils/app.py
flika/utils/custom_widgets.py
flika/utils/imports.py
flika/utils/misc.py
flika/utils/pyqtgraph_patch.py
flika/utils/system_info.py
flika/utils/thread_manager.py
flika/utils/io/__init__.py
flika/utils/io/tifffile.py
flika-0.3.3.dist-info/licenses/LICENSE
flika-0.3.3.dist-info/METADATA
flika-0.3.3.dist-info/WHEEL
flika-0.3.3.dist-info/entry_points.txt
flika-0.3.3.dist-info/top_level.txt
flika-0.3.3.dist-info/RECORD
